{
  "MenuDimensions": {
    "Width": 1100,
    "Height": 920
  },
  "Title": {
    "Text": "奇点存储 (Singularity Storage)",
    "OffsetY": 50
  },
  "Header": {
    "OffsetY": 100,
    "Height": 52,
    "Padding": 32
  },
  "SearchBar": {
    "OffsetX": 180,
    "Width": 500,
    "Height": 40,
    "Placeholder": "Search..."
  },
  "PageButtons": {
    "PrevOffsetX": 44,
    "NextOffsetX": 108,
    "Width": 44,
    "Height": 40
  },
  "StorageInventory": {
    "OffsetX": 60,
    "OffsetY": 180,
    "Columns": 14,
    "Rows": 5,
    "SlotSpacing": 4
  },
  "PlayerInventory": {
    "OffsetX": 60,
    "OffsetFromBottom": 240
  },
  "Separator": {
    "OffsetFromInventory": 40,
    "Height": 16
  },
  "StoreAllButton": {
    "OffsetFromRight": 160,
    "OffsetFromBottom": 816,
    "Size": 48,
    "TextureSource": {
      "X": 103,
      "Y": 469,
      "Width": 16,
      "Height": 16
    }
  },
  "FillStacksButton": {
    "OffsetFromRight": 96,
    "OffsetFromBottom": 816,
    "Size": 48,
    "TextureSource": {
      "X": 103,
      "Y": 469,
      "Width": 16,
      "Height": 16
    }
  },
  "OkButton": {
    "OffsetFromRight": 100,
    "OffsetFromBottom": 100,
    "Size": 64
  },
  "LoadingText": {
    "Text": "加载中...",
    "OffsetY": 120
  }
}
